{"_id": "5ebce75e80771d653f96d969", "uuid": "linkedin|w9qvxKf7y5", "cableid": "83", "name": "BAHAMAS-2", "notes": "", "systemLength": "470", "activationDateTime": "1997-07-01T07:00:00.000Z", "urls": ["https://atlantic-cable.com/Cables/CableTimeLine/index1951.htm", "https://licensing.fcc.gov/ibfsweb/ib.page.FetchPN?report_key=15465852", "https://licensing.fcc.gov/cgi-bin/ws.exe/prod/ib/forms/reports/swr031b.hts?q_set=V_SITE_ANTENNA_FREQ.file_numberC/File+Number/%3D/SCLSTA2022030300010&prepare=&column=V_SITE_ANTENNA_FREQ.file_numberC/File+Number"], "terrestrial": false, "capacityTBPS": "0", "litCapacity": [{"year": "2006-12-31T23:00:00.000Z", "cap": 0.0025}, {"year": "2007-12-31T23:00:00.000Z", "cap": 0.0025}, {"year": "2008-12-31T23:00:00.000Z", "cap": 0.0025}, {"year": "2009-12-31T23:00:00.000Z", "cap": 0.0025}, {"year": "2010-12-31T23:00:00.000Z", "cap": 0.0025}, {"year": "2011-12-31T23:00:00.000Z", "cap": 0.06}, {"year": "2012-12-31T23:00:00.000Z", "cap": 0.06}, {"year": "2013-12-31T23:00:00.000Z", "cap": 0.06}, {"year": "2014-12-31T23:00:00.000Z", "cap": 0.06}, {"year": "2015-12-31T23:00:00.000Z", "cap": 0.06}, {"year": "2016-12-31T23:00:00.000Z", "cap": 0.06}, {"year": "2017-12-31T23:00:00.000Z", "cap": 0.1}, {"year": "2018-12-31T23:00:00.000Z", "cap": 0.1}], "fiberPairs": "0", "category": "active", "facilities": [], "owners": [{"_id": "5ebcd71e8afb865ea6fb05b5", "name": "AT&T"}, {"_id": "5ebcd7218afb865ea6fb1995", "name": "Telefonica"}, {"_id": "5ebcd7218afb865ea6fb195d", "name": "Verizon"}], "tags": "", "rgDate": "2020-05-14T06:38:22.444Z", "uDate": "2022-05-30T12:47:27.550Z", "cls": [{"_id": "5ef0637c5aa1025277a80772", "name": "Eight-Mile Rock,  Bahamas"}, {"_id": "5ef0637c5aa1025277a8090b", "name": "Nassau,  Bahamas"}, {"_id": "5ef0637c5aa1025277a80abf", "name": "Vero Beach, FL, US"}], "slug": "bahamas-2", "knownUsers": [], "cluster": {"type": "FeatureCollection", "features": [{"type": "Feature", "properties": {"name": "Eight-Mile Rock", "id": "5ef0637c5aa1025277a80772", "_id": "5ef0637c5aa1025277a80772"}, "geometry": {"type": "Point", "coordinates": [-78.802861, 26.539621]}}, {"type": "Feature", "properties": {"name": "Nassau", "id": "5ef0637c5aa1025277a8090b", "_id": "5ef0637c5aa1025277a8090b"}, "geometry": {"type": "Point", "coordinates": [-77.340252, 25.067039]}}, {"type": "Feature", "properties": {"name": "Vero Beach, FL", "id": "5ef0637c5aa1025277a80abf", "_id": "5ef0637c5aa1025277a80abf"}, "geometry": {"type": "Point", "coordinates": [-80.394267, 27.638388]}}]}, "networks": [], "organizations": [], "alert": 0, "RFS": "August 1997"}