{"_id": "5ebce77580771d653f9705f1", "uuid": "linkedin|w9qvxKf7y5", "cableid": "473", "name": "FLY-LION3", "notes": "", "systemLength": "400", "activationDateTime": "2019-09-30T22:00:00.000Z", "urls": ["https://www.orange.com/en/newsroom/press-releases/high-speed-broadband-submarine-cable-fly-lion3-makes-landfall-mayotte", "https://www.fomsn.com/submarine/tm/fly-lion-iii-lands-in-mayotte/", "https://twitter.com/philBE2/status/1098949905568153600", "https://twitter.com/philBE2/status/1098951039972241409/photo/1", "https://twitter.com/philBE2/status/1099991913468514304/photo/2"], "terrestrial": false, "capacityTBPS": "4", "litCapacity": [], "fiberPairs": "2", "category": "active", "facilities": [], "owners": [{"_id": "61fb8bfa12b8ed7497b05330", "name": "Comoros Cables"}, {"_id": "5ebcd71b8afb865ea6fae569", "name": "Orange"}, {"_id": "5f215e01838eb337c714327b", "name": "SRR/SFR R\u00e9union (Soci\u00e9t\u00e9 R\u00e9unionnaise du Radiot\u00e9l\u00e9phone)"}], "tags": "", "rgDate": "2020-05-14T06:38:45.522Z", "uDate": "2022-02-03T08:02:36.843Z", "cls": [{"_id": "5ef0637c5aa1025277a80810", "name": "Kaweni,  Mayotte"}, {"_id": "5ef0637c5aa1025277a808f1", "name": "Moroni,  Comoros"}], "slug": "fly-lion3", "knownUsers": [], "cluster": {"type": "FeatureCollection", "features": [{"type": "Feature", "properties": {"name": "Kaweni", "id": "5ef0637c5aa1025277a80810", "_id": "5ef0637c5aa1025277a80810"}, "geometry": {"type": "Point", "coordinates": [45.165854, -12.817099]}}, {"type": "Feature", "properties": {"name": "Moroni", "id": "5ef0637c5aa1025277a808f1", "_id": "5ef0637c5aa1025277a808f1"}, "geometry": {"coordinates": [43.26453364663394, -11.677832251837868], "type": "Point"}}]}, "networks": [], "organizations": [], "alert": 0, "RFS": "October 2019"}