{"_id": "621c83719bb417322e5671dd", "uuid": "linkedin|w9qvxKf7y5", "name": "Link 4 Phase-2", "slug": "link-4-phase-2", "notes": "", "systemLength": "300", "activationDateTime": "2005-02-28T23:00:00.000Z", "urls": [], "terrestrial": false, "capacityTBPS": "0", "litCapacity": [], "fiberPairs": "0", "category": "active", "facilities": [], "owners": [{"_id": "5ebcd7198afb865ea6fadaff", "name": "PT. XL AXIATA, Tbk"}], "knownUsers": [], "cls": [{"_id": "5ef0637c5aa1025277a808d6", "name": "Mentigi,  Indonesia"}, {"_id": "5ef0637c5aa1025277a80a3f", "name": "Sungailiat,  Indonesia"}], "tags": "", "rgDate": "2022-02-28T08:10:25.063Z", "uDate": "2022-02-28T08:10:25.063Z", "cluster": {"type": "FeatureCollection", "features": [{"type": "Feature", "properties": {"name": "Mentigi", "id": "5ef0637c5aa1025277a808d6", "_id": "5ef0637c5aa1025277a808d6"}, "geometry": {"type": "Point", "coordinates": [107.696366, -3.195985]}}, {"type": "Feature", "properties": {"name": "Sungailiat", "id": "5ef0637c5aa1025277a80a3f", "_id": "5ef0637c5aa1025277a80a3f"}, "geometry": {"type": "Point", "coordinates": [106.1325, -1.851503]}}]}, "networks": [], "organizations": [], "alert": 0, "RFS": "March 2005"}