{"_id": "5ebce77580771d653f970689", "uuid": "linkedin|w9qvxKf7y5", "cableid": "59", "name": "Lower Indian Ocean Network (LION)", "notes": "", "systemLength": "1090", "activationDateTime": "2009-10-31T23:00:00.000Z", "urls": ["https://lion-submarinesystem.com/", "https://web.archive.org/web/20140220175230/http://lion.orange.com/default/EN/all/lion_en/"], "terrestrial": false, "capacityTBPS": "1.28", "litCapacity": [], "fiberPairs": "0", "category": "active", "facilities": [], "owners": [{"_id": "5ebcd71c8afb865ea6faf2da", "name": "Mauritius Telecom Ltd"}, {"_id": "5ebcd71b8afb865ea6fae569", "name": "Orange"}, {"_id": "5ebcd71c8afb865ea6faedce", "name": "Orange Madagascar"}], "tags": "", "rgDate": "2020-05-14T06:38:45.579Z", "uDate": "2022-05-03T06:42:11.593Z", "cls": [{"_id": "5ef0637c5aa1025277a809cb", "name": "Sainte Marie,  R\u00e9union"}, {"_id": "5ef0637c5aa1025277a80a6c", "name": "Terre Rouge,  Mauritius"}, {"_id": "5ef0637c5aa1025277a80a7b", "name": "Toamasina,  Madagascar"}], "knownUsers": [], "slug": "lower-indian-ocean-network-lion", "cluster": {"type": "FeatureCollection", "features": [{"type": "Feature", "properties": {"name": "Sainte Marie", "id": "5ef0637c5aa1025277a809cb", "_id": "5ef0637c5aa1025277a809cb"}, "geometry": {"type": "Point", "coordinates": [55.549931, -20.897368]}}, {"type": "Feature", "properties": {"name": "Terre Rouge", "id": "5ef0637c5aa1025277a80a6c", "_id": "5ef0637c5aa1025277a80a6c"}, "geometry": {"type": "Point", "coordinates": [57.510086, -20.077813]}}, {"type": "Feature", "properties": {"name": "Toamasina", "id": "5ef0637c5aa1025277a80a7b", "_id": "5ef0637c5aa1025277a80a7b"}, "geometry": {"type": "Point", "coordinates": [49.400325, -18.146173]}}]}, "networks": [], "organizations": [], "alert": 0, "RFS": "November 2009"}