{"_id": "5ebce77580771d653f97068d", "uuid": "linkedin|w9qvxKf7y5", "cableid": "594", "name": "Pan European Crossing (UK-Ireland)", "notes": "", "systemLength": "495", "activationDateTime": "2000-08-31T22:00:00.000Z", "urls": [], "terrestrial": false, "capacityTBPS": "0", "litCapacity": [], "fiberPairs": "0", "category": "active", "facilities": [], "owners": [{"_id": "5ebcd71f8afb865ea6fb07c1", "name": "Lumen Technologies, Inc (f.k.a CenturyLink)"}], "tags": "", "rgDate": "2020-05-14T06:38:45.580Z", "uDate": "2022-05-03T06:48:19.865Z", "cls": [{"_id": "5ef0637c5aa1025277a806a3", "name": "Ballinesker,  Ireland"}, {"_id": "5ef0637c5aa1025277a806a5", "name": "Ballygrangans,  Ireland"}, {"_id": "5ef0637c5aa1025277a806e6", "name": "Bude,  United Kingdom"}, {"_id": "5ef0637c5aa1025277a80ad3", "name": "Whitesands Bay,  United Kingdom"}], "slug": "pan-european-crossing-uk-ireland", "knownUsers": [], "cluster": {"type": "FeatureCollection", "features": [{"type": "Feature", "properties": {"name": "Ballinesker", "id": "5ef0637c5aa1025277a806a3", "_id": "5ef0637c5aa1025277a806a3"}, "geometry": {"type": "Point", "coordinates": [-6.364859, 52.401462]}}, {"type": "Feature", "properties": {"name": "Ballygrangans", "id": "5ef0637c5aa1025277a806a5", "_id": "5ef0637c5aa1025277a806a5"}, "geometry": {"type": "Point", "coordinates": [-6.558804, 52.184079]}}, {"type": "Feature", "properties": {"name": "Bude", "id": "5ef0637c5aa1025277a806e6", "_id": "5ef0637c5aa1025277a806e6"}, "geometry": {"coordinates": [-4.541133928268528, 50.82085317169804], "type": "Point"}}, {"type": "Feature", "properties": {"name": "Whitesands Bay", "id": "5ef0637c5aa1025277a80ad3", "_id": "5ef0637c5aa1025277a80ad3"}, "geometry": {"type": "Point", "coordinates": [-5.698453, 50.078514]}}]}, "networks": [], "organizations": [], "alert": 0, "RFS": "September 2000"}