{"_id": "5ebce77580771d653f9706bf", "uuid": "", "cableid": "626", "name": "Angola Cables", "notes": "", "systemLength": "140", "activationDateTime": "2015-01-01T00:00:00.000Z", "urls": ["http://www.angolacables.co.ao"], "terrestrial": true, "capacityTBPS": "0", "litCapacity": [], "fiberPairs": "0", "category": "", "facilities": [], "owners": [], "tags": [], "rgDate": "2020-05-14T06:38:45.598Z", "uDate": "2020-05-14T06:38:45.598Z", "cls": [], "slug": "angola-cables", "cluster": {"type": "FeatureCollection", "features": []}, "networks": [], "organizations": [], "knownUsers": [], "alert": 0, "RFS": "February 2015"}