{"_id": "5ebce77580771d653f970655", "uuid": "auth0|5e5bc34834963c0d4787cdf8", "cableid": "531", "name": "Jambi-Batam Cable System (JIBA)", "notes": "", "systemLength": "267", "activationDateTime": "2013-12-31T23:00:00.000Z", "urls": ["https://www.moratelindo.co.id/eng/service-connectivity.html", "https://www.moratelindo.co.id/eng/img/moratelindo/backbone/international-backbone-network.jpg"], "terrestrial": false, "capacityTBPS": "0.56", "litCapacity": [], "fiberPairs": "0", "category": "active", "facilities": [], "owners": [{"_id": "5ebcd7218afb865ea6fb1997", "name": "Indosat Ooredoo"}, {"_id": "5ebcd71e8afb865ea6fb055c", "name": "Moratelindo"}, {"_id": "5ebcd7198afb865ea6fadaff", "name": "PT. XL AXIATA, Tbk"}], "tags": "", "rgDate": "2020-05-14T06:38:45.563Z", "uDate": "2022-04-21T12:47:58.719Z", "cls": [{"_id": "5ef0637c5aa1025277a8084e", "name": "Kuala Tungkal,  Indonesia"}, {"_id": "5ef0637c5aa1025277a80a5a", "name": "Tanjung Pinggir,  Indonesia"}], "slug": "jambi-batam-cable-system-jiba", "knownUsers": [], "cluster": {"type": "FeatureCollection", "features": [{"type": "Feature", "properties": {"name": "Kuala Tungkal", "id": "5ef0637c5aa1025277a8084e", "_id": "5ef0637c5aa1025277a8084e"}, "geometry": {"type": "Point", "coordinates": [103.46319, -0.823452]}}, {"type": "Feature", "properties": {"name": "Tanjung Pinggir", "id": "5ef0637c5aa1025277a80a5a", "_id": "5ef0637c5aa1025277a80a5a"}, "geometry": {"type": "Point", "coordinates": [103.959722, 1.133481]}}]}, "networks": [], "organizations": [], "alert": 0, "RFS": null}